{
  "registry": "@shadcnblocks",
  "component": "contact19",
  "url": "https://shadcnblocks.com/r/contact19.json",
  "error": "HTTP 401 Unauthorized",
  "item": {
    "name": "contact19",
    "type": "registry:block",
    "title": "Contact",
    "description": "A contact component with a two-column layout; one for text and buttons, and one for a full-height image. Features bold headings, a contact number, email, and a \"Get in touch\" button with an icon.",
    "dependencies": [
      "lucide-react"
    ],
    "registryDependencies": [
      "button"
    ],
    "files": [
      {
        "path": "code/block/contact19.tsx",
        "type": "registry:block"
      }
    ]
  },
  "fetchedAt": "2026-01-03T11:28:32.486Z"
}