{
  "$schema": "https://ui.shadcn.com/schema/registry-item.json",
  "name": "textarea",
  "dependencies": ["react-aria-components"],
  "registryDependencies": ["https://taki-ui.com/r/utils.json"],
  "files": [
    {
      "path": "registry/new-york/ui/textarea.tsx",
      "content": "\"use client\"\n\nimport * as React from \"react\"\nimport { TextArea as RACTextarea } from \"react-aria-components\"\n\nimport { cn } from \"@/lib/utils\"\n\nfunction Textarea({ className, ...props }: React.ComponentProps<\"textarea\">) {\n  return (\n    <RACTextarea\n      data-slot=\"textarea\"\n      className={cn(\n        \"border-input placeholder:text-muted-foreground focus-visible:border-ring focus-visible:ring-ring/50 aria-invalid:ring-destructive/20 dark:aria-invalid:ring-destructive/40 aria-invalid:border-destructive dark:bg-input/30 flex field-sizing-content min-h-16 w-full rounded-md border bg-transparent px-3 py-2 text-base shadow-xs transition-[color,box-shadow] outline-none focus-visible:ring-[3px] disabled:cursor-not-allowed disabled:opacity-50 md:text-sm\",\n        \"focus:border-ring focus:ring-ring/50 focus:ring-[3px]\",\n        className\n      )}\n      {...props}\n    />\n  )\n}\n\nexport { Textarea }\n",
      "type": "registry:ui"
    }
  ],
  "type": "registry:ui"
}
