{
  "$schema": "https://ui.shadcn.com/schema/registry-item.json",
  "name": "medusa",
  "title": "medusa",
  "files": [
    {
      "path": "././static/components-generated/medusa.tsx",
      "content": "import type { SVGProps } from \"react\";\n\nconst Medusa = (props: SVGProps<SVGSVGElement>) => (\n  <svg {...props} viewBox=\"0 0 256 277\" preserveAspectRatio=\"xMidYMid\">\n    <defs>\n      <linearGradient\n        id=\"a\"\n        x1=\"-66.697%\"\n        x2=\"108.63%\"\n        y1=\"81.87%\"\n        y2=\"34.419%\"\n      >\n        <stop offset=\"26.563%\" stop-color=\"#592EE1\" />\n        <stop offset=\"100%\" stop-color=\"#B836D9\" />\n      </linearGradient>\n    </defs>\n    <path\n      fill=\"url(#a)\"\n      d=\"M223.517 44.823 161.174 8.85a65.565 65.565 0 0 0-65.792 0l-62.63 35.973C12.642 56.623 0 78.495 0 101.806v72.235c0 23.6 12.641 45.183 32.752 56.982l62.343 36.263a65.565 65.565 0 0 0 65.791 0l62.343-36.263c20.399-11.799 32.752-33.383 32.752-56.982v-72.235c.575-23.311-12.066-45.183-32.464-56.983Zm-95.383 157.422c-35.337 0-64.067-28.78-64.067-64.177 0-35.399 28.73-64.178 64.067-64.178 35.338 0 64.355 28.779 64.355 64.178 0 35.398-28.73 64.177-64.355 64.177Z\"\n    />\n  </svg>\n);\n\nexport { Medusa };\n",
      "type": "registry:component",
      "target": "components/ui/svgs/medusa.tsx"
    }
  ],
  "type": "registry:component"
}
