{
  "registry": "@shadcnblocks",
  "component": "logos5",
  "url": "https://shadcnblocks.com/r/logos5.json",
  "error": "HTTP 401 Unauthorized",
  "item": {
    "name": "logos5",
    "type": "registry:block",
    "title": "Logos",
    "description": "A dual-row logo showcase component, featuring 4 logos on the top row and 5 on the bottom, with hover effects and external links.",
    "dependencies": [],
    "registryDependencies": [],
    "files": [
      {
        "path": "code/block/logos5.tsx",
        "type": "registry:block"
      }
    ]
  },
  "fetchedAt": "2026-01-03T11:28:54.184Z"
}