{
  "$schema": "https://ui.shadcn.com/schema/registry-item.json",
  "name": "p-textarea-4",
  "type": "registry:block",
  "description": "Disabled textarea",
  "registryDependencies": ["@coss/textarea"],
  "files": [
    {
      "path": "registry/default/particles/p-textarea-4.tsx",
      "content": "import { Textarea } from \"@/registry/default/ui/textarea\";\n\nexport default function Particle() {\n  return <Textarea disabled placeholder=\"Can't type here\" />;\n}\n",
      "type": "registry:block"
    }
  ],
  "meta": {
    "className": "**:data-[slot=preview]:w-full **:data-[slot=preview]:max-w-64"
  },
  "categories": ["textarea"]
}
