{
  "$schema": "https://ui.shadcn.com/schema/registry-item.json",
  "name": "utils",
  "title": "Utils",
  "description": "Library utility: utils",
  "dependencies": ["clsx", "tailwind-merge"],
  "registryDependencies": [],
  "files": [
    {
      "path": "registry/optics/lib/utils.js",
      "content": "import { clsx } from \"clsx\";\nimport { twMerge } from \"tailwind-merge\";\n\nexport function cn(...inputs) {\n\treturn twMerge(clsx(inputs));\n}\n",
      "type": "registry:lib",
      "target": "lib/utils.js"
    }
  ],
  "type": "registry:lib"
}
