{
  "$schema": "https://ui.shadcn.com/schema/registry-item.json",
  "name": "css-colorarea",
  "type": "registry:ui",
  "title": "ColorArea",
  "dependencies": ["react-aria-components"],
  "registryDependencies": [
    "https://react-aria.adobe.com/registry/css-colorthumb.json"
  ],
  "files": [
    {
      "path": "components/ui/ColorArea.tsx",
      "type": "registry:ui",
      "content": "'use client';\nimport {\n  ColorArea as AriaColorArea,\n  ColorAreaProps\n} from 'react-aria-components';\n\nimport {ColorThumb} from '@/registry/react-aria/ui/ColorThumb';\nimport './ColorArea.css';\n\nexport function ColorArea(props: ColorAreaProps) {\n  return (\n    (\n      <AriaColorArea {...props}>\n        <ColorThumb />\n      </AriaColorArea>\n    )\n  );\n}\n"
    },
    {
      "path": "components/ui/ColorArea.css",
      "type": "registry:component",
      "content": "\n.react-aria-ColorArea {\n  width: 100%;\n  max-width: calc(var(--spacing) * 56);\n  aspect-ratio: 1/1;\n  border-radius: var(--radius);\n  flex-shrink: 0;\n}\n\n.react-aria-ColorArea {\n  &[data-disabled] {\n    background: gray !important;\n  }\n}\n"
    }
  ]
}
