{
  "$schema": "https://ui.shadcn.com/schema/registry-item.json",
  "extends": "none",
  "name": "toggle-disabled-demo",
  "title": "Toggle Disabled",
  "description": "toggle-disabled-demo",
  "registryDependencies": ["https://intentui.com/r/toggle"],
  "files": [
    {
      "path": "src/components/docs/buttons/toggle/toggle-disabled-demo.tsx",
      "content": "\"use client\"\n\nimport { Toggle } from \"@/components/ui/toggle\"\n\nexport default function ToggleDisabledDemo() {\n  return <Toggle isDisabled>Toggle</Toggle>\n}\n",
      "type": "registry:page",
      "target": "app/toggle-disabled-demo/page.tsx"
    }
  ],
  "type": "registry:page"
}
