{
  "$schema": "https://ui.shadcn.com/schema/registry-item.json",
  "extends": "none",
  "name": "button-pending-demo",
  "title": "Button Pending",
  "description": "button-pending-demo",
  "dependencies": ["@heroicons/react"],
  "registryDependencies": [
    "https://intentui.com/r/button",
    "https://intentui.com/r/progress-circle"
  ],
  "files": [
    {
      "path": "src/components/docs/buttons/button/button-pending-demo.tsx",
      "content": "\"use client\"\n\nimport { PlusIcon } from \"@heroicons/react/20/solid\"\nimport { useState } from \"react\"\nimport { Button } from \"@/components/ui/button\"\nimport { ProgressCircle } from \"@/components/ui/progress-circle\"\n\nexport default function ButtonPendingDemo() {\n  const [isLoading, setLoading] = useState(false)\n\n  const handlePress = () => {\n    setLoading(true)\n    setTimeout(() => {\n      setLoading(false)\n    }, 4500)\n  }\n  return (\n    <Button onPress={handlePress} isPending={isLoading}>\n      {({ isPending }) => (\n        <>\n          {isPending ? <ProgressCircle isIndeterminate aria-label=\"Creating...\" /> : <PlusIcon />}\n          {isLoading ? \"Creating...\" : \"Create\"}\n        </>\n      )}\n    </Button>\n  )\n}\n",
      "type": "registry:page",
      "target": "app/button-pending-demo/page.tsx"
    }
  ],
  "type": "registry:page"
}
