{
  "registry": "@shadcnblocks",
  "component": "hero101",
  "url": "https://shadcnblocks.com/r/hero101.json",
  "error": "HTTP 401 Unauthorized",
  "item": {
    "name": "hero101",
    "type": "registry:block",
    "title": "Hero",
    "description": "A component with a promotional header, featuring a title, description, start button, and demo video button that triggers a modal with a video player. It also displays partner logos below.",
    "dependencies": [
      "lucide-react",
      "react"
    ],
    "registryDependencies": [
      "aspect-ratio",
      "button",
      "dialog"
    ],
    "files": [
      {
        "path": "code/block/hero101.tsx",
        "type": "registry:block"
      }
    ]
  },
  "fetchedAt": "2026-01-03T11:28:46.883Z"
}